{"type":"Feature", "fullDetails":{"firstname":"Gary", "lastname":"Russo", "email":"garyrusso@hotmail.com", "city":"New York", "state":"NY", "industry":"Financial Services", "company":"Broadridge", "phone":"(201) 536-4432", "accountType":null, "address":"201 West 17 Street 7C", "country":"United States of America", "numEmployees":null, "username":"garyrusso", "region":null, "hasAccessToEAML9":true, "postalCode":"10011", "registeredForEAML8":true, "registeredForNoSQLforDummies":false, "registrationDate":"2015-02-19", "revenueRange":"Over $5B", "leadSource":"FY16Q1 - MLE - MLW - San Francisco", "website":"broadridge.com", "lastUpdated":"2016-08-10T13:55:45.489697-07:00", "dateAdded":"2016-08-03T09:50:42.947714-07:00"}, "source":"<leadRecord xmlns:SOAP-ENV=\"http://schemas.xmlsoap.org/soap/envelope/\" xmlns:xsi=\"http://www.w3.org/2001/XMLSchema-instance\" xmlns:ns1=\"http://www.marketo.com/mktows/\"><Id>2433427</Id><Email>garyrusso@hotmail.com</Email><ForeignSysPersonId xsi:nil=\"true\"/><ForeignSysType xsi:nil=\"true\"/><leadAttributeList><attribute><attrName>Account_Main_Industry__c</attrName><attrType>string</attrType><attrValue>Consulting</attrValue></attribute><attribute><attrName>Account_Type__c</attrName><attrType>string</attrType><attrValue>Prospect</attrValue></attribute><attribute><attrName>Address</attrName><attrType>text</attrType><attrValue>201 West 17 Street 7C</attrValue></attribute><attribute><attrName>agreedtoEAML8TC</attrName><attrType>boolean</attrType><attrValue>1</attrValue></attribute><attribute><attrName>amazonIdforEAML8</attrName><attrType>string</attrType><attrValue>3588-9260-7696</attrValue></attribute><attribute><attrName>AnnualRevenue</attrName><attrType>currency</attrType><attrValue>9360000000</attrValue></attribute><attribute><attrName>audience_segment__c</attrName><attrType>string</attrType><attrValue>Software &amp; Technology</attrValue></attribute><attribute><attrName>Audience__c</attrName><attrType>string</attrType><attrValue>Enterprise Business</attrValue></attribute><attribute><attrName>b2b__c</attrName><attrType>boolean</attrType><attrValue>1</attrValue></attribute><attribute><attrName>b2c__c</attrName><attrType>boolean</attrType><attrValue>1</attrValue></attribute><attribute><attrName>BillingCity</attrName><attrType>string</attrType><attrValue>New York</attrValue></attribute><attribute><attrName>BillingCountry</attrName><attrType>string</attrType><attrValue>United States of America</attrValue></attribute><attribute><attrName>BillingPostalCode</attrName><attrType>string</attrType><attrValue>10011</attrValue></attribute><attribute><attrName>BillingState</attrName><attrType>string</attrType><attrValue>NY</attrValue></attribute><attribute><attrName>City</attrName><attrType>string</attrType><attrValue>New York</attrValue></attribute><attribute><attrName>Comm_or_PS__c</attrName><attrType>string</attrType><attrValue>Commercial</attrValue></attribute><attribute><attrName>Comm_or_PS__c_account</attrName><attrType>string</attrType><attrValue>Commercial</attrValue></attribute><attribute><attrName>Company</attrName><attrType>string</attrType><attrValue>Broadridge</attrValue></attribute><attribute><attrName>Contracts_To_Send__c</attrName><attrType>string</attrType><attrValue>Mutual Non-Disclosure Agreement</attrValue></attribute><attribute><attrName>Country</attrName><attrType>string</attrType><attrValue>United States of America</attrValue></attribute><attribute><attrName>Country__c</attrName><attrType>string</attrType><attrValue>United States of America</attrValue></attribute><attribute><attrName>dba_Company_Name__c</attrName><attrType>string</attrType><attrValue>Broadridge Financial Solutions (India) Private Limited</attrValue></attribute><attribute><attrName>DC_Clean_Status_Final__c</attrName><attrType>string</attrType><attrValue>Different</attrValue></attribute><attribute><attrName>DC_Clean_Status__c</attrName><attrType>string</attrType><attrValue>Different</attrValue></attribute><attribute><attrName>DC_Clean_Status__c_lead</attrName><attrType>string</attrType><attrValue>NotFound</attrValue></attribute><attribute><attrName>DC_Company_Name__c</attrName><attrType>string</attrType><attrValue>Pocket XP, Inc.</attrValue></attribute><attribute><attrName>DC_Description__c</attrName><attrType>text</attrType><attrValue>Pocket XP, Inc. is currently a sole proprietorship single person consulting organization.\n\nGary Russo is a former MarkLogic employee, and is the President of this entity.</attrValue></attribute><attribute><attrName>DC_Email__c</attrName><attrType>email</attrType><attrValue>garyrusso@hotmail.com</attrValue></attribute><attribute><attrName>DC_Phone__c</attrName><attrType>phone</attrType><attrValue>(201) 536-4432</attrValue></attribute><attribute><attrName>DC_Phone__c_account</attrName><attrType>phone</attrType><attrValue>(347) 678-3261</attrValue></attribute><attribute><attrName>DC_Title__c</attrName><attrType>string</attrType><attrValue>NoSQL Architect</attrValue></attribute><attribute><attrName>ddc_prospector__Sourced_from_Data_com__c_account</attrName><attrType>integer</attrType><attrValue>0</attrValue></attribute><attribute><attrName>ddc_prospector__Sourced_from_Data_com__c_contact</attrName><attrType>integer</attrType><attrValue>0</attrValue></attribute><attribute><attrName>demandbase_data_source__c</attrName><attrType>string</attrType><attrValue>company</attrValue></attribute><attribute><attrName>demandbase_ip__c</attrName><attrType>string</attrType><attrValue>115.112.123.195</attrValue></attribute><attribute><attrName>demandbase_sid__c</attrName><attrType>integer</attrType><attrValue>116158320</attrValue></attribute><attribute><attrName>eAML8confirmationlink</attrName><attrType>text</attrType><attrValue>https://ea.marklogic.com/account/confirm/73a78785eff6171b36d597b311018415c63cc553/</attrValue></attribute><attribute><attrName>EA_ML9username</attrName><attrType>string</attrType><attrValue>garyrusso</attrValue></attribute><attribute><attrName>email_domain__c</attrName><attrType>string</attrType><attrValue>@hotmail.com</attrValue></attribute><attribute><attrName>Employee_Range__c</attrName><attrType>string</attrType><attrValue>Enterprise</attrValue></attribute><attribute><attrName>Exclude_Domain__c</attrName><attrType>boolean</attrType><attrValue>1</attrValue></attribute><attribute><attrName>FirstName</attrName><attrType>string</attrType><attrValue>Gary</attrValue></attribute><attribute><attrName>FullName__c</attrName><attrType>string</attrType><attrValue>Russo, Gary</attrValue></attribute><attribute><attrName>Geo__c</attrName><attrType>string</attrType><attrValue>AMS</attrValue></attribute><attribute><attrName>HasAccessToEAML9</attrName><attrType>boolean</attrType><attrValue>1</attrValue></attribute><attribute><attrName>Industry</attrName><attrType>string</attrType><attrValue>Computer Software</attrValue></attribute><attribute><attrName>InferredCompany</attrName><attrType>string</attrType><attrValue>West Publishing Corporation</attrValue></attribute><attribute><attrName>InferredCountry</attrName><attrType>string</attrType><attrValue>United States</attrValue></attribute><attribute><attrName>ISO2__c</attrName><attrType>string</attrType><attrValue>IN</attrValue></attribute><attribute><attrName>LastModbyOwner__c</attrName><attrType>integer</attrType><attrValue>0</attrValue></attribute><attribute><attrName>LastName</attrName><attrType>string</attrType><attrValue>Russo</attrValue></attribute><attribute><attrName>LeadScore</attrName><attrType>integer</attrType><attrValue>3728</attrValue></attribute><attribute><attrName>LeadSource</attrName><attrType>string</attrType><attrValue>MarkLogic World</attrValue></attribute><attribute><attrName>LeadStatus</attrName><attrType>string</attrType><attrValue>Converted</attrValue></attribute><attribute><attrName>Lead_Age_calc__c</attrName><attrType>integer</attrType><attrValue>115</attrValue></attribute><attribute><attrName>Lead_Score_Behavior__c</attrName><attrType>integer</attrType><attrValue>3591</attrValue></attribute><attribute><attrName>Lead_Score_Demographic__c</attrName><attrType>integer</attrType><attrValue>10</attrValue></attribute><attribute><attrName>Lead_Score_Total__c</attrName><attrType>integer</attrType><attrValue>3601</attrValue></attribute><attribute><attrName>License_Host__c</attrName><attrType>text</attrType><attrValue>ps5.demo.marklogic.com</attrValue></attribute><attribute><attrName>License_Num_of_CPUs__c</attrName><attrType>integer</attrType><attrValue>1</attrValue></attribute><attribute><attrName>License_Platform__c</attrName><attrType>text</attrType><attrValue>linux</attrValue></attribute><attribute><attrName>license_type__c</attrName><attrType>string</attrType><attrValue>Developer</attrValue></attribute><attribute><attrName>MainPhone</attrName><attrType>string</attrType><attrValue>(347) 678-3261</attrValue></attribute><attribute><attrName>Main_Industry__c</attrName><attrType>string</attrType><attrValue>Financial Services</attrValue></attribute><attribute><attrName>Main_Industry__c_account</attrName><attrType>string</attrType><attrValue>Consulting</attrValue></attribute><attribute><attrName>Manager_email__c</attrName><attrType>string</attrType><attrValue>dominic.spitz@marklogic.com</attrValue></attribute><attribute><attrName>markLogicContactEmail</attrName><attrType>email</attrType><attrValue>dave.cassel@marklogic.com</attrValue></attribute><attribute><attrName>MktoCompanyNotes</attrName><attrType>text</attrType><attrValue>Pocket XP, Inc. is currently a sole proprietorship single person consulting organization.\n\nGary Russo is a former MarkLogic employee, and is the President of this entity.</attrValue></attribute><attribute><attrName>mkto_si__Sales_Insight__c</attrName><attrType>string</attrType><attrValue>&lt;a href=\"/apex/Contact_Full_List?id=0034000001fKWoQ\" target=\"_blank\"&gt;&lt;img src=\"https://www.marketo.com/salesforce/images/applicationLink.png\" alt=\"Sales Insight\" border=\"0\"/&gt;&lt;/a&gt;</attrValue></attribute><attribute><attrName>MobilePhone</attrName><attrType>phone</attrType><attrValue>(347) 678-3261</attrValue></attribute><attribute><attrName>Newsletter_Sub__c</attrName><attrType>string</attrType><attrValue>none</attrValue></attribute><attribute><attrName>NumberOfEmployees</attrName><attrType>integer</attrType><attrValue>6700</attrValue></attribute><attribute><attrName>Num_of_Closed_Won_Opps__c</attrName><attrType>integer</attrType><attrValue>0</attrValue></attribute><attribute><attrName>Num_of_References__c</attrName><attrType>integer</attrType><attrValue>0</attrValue></attribute><attribute><attrName>of_References__c</attrName><attrType>integer</attrType><attrValue>0</attrValue></attribute><attribute><attrName>On24_EventTitle__c</attrName><attrType>text</attrType><attrValue>Get Smart About Semantics in Healthcare</attrValue></attribute><attribute><attrName>ownermanageremail__c</attrName><attrType>email</attrType><attrValue>dominic.spitz@marklogic.com</attrValue></attribute><attribute><attrName>Owner_Actual_Name__c</attrName><attrType>string</attrType><attrValue>00540000003STbqAAG</attrValue></attribute><attribute><attrName>Owner_is_Active_T_F__c</attrName><attrType>boolean</attrType><attrValue>1</attrValue></attribute><attribute><attrName>Owner_Name__c</attrName><attrType>string</attrType><attrValue>Cole, Annette</attrValue></attribute><attribute><attrName>Owner_Queue_Name__c</attrName><attrType>string</attrType><attrValue>Jeff Faraday</attrValue></attribute><attribute><attrName>Owner_Type__c</attrName><attrType>string</attrType><attrValue>Alliances</attrValue></attribute><attribute><attrName>Owner_Type__c_account</attrName><attrType>string</attrType><attrValue>Sales_Channel</attrValue></attribute><attribute><attrName>Owner_User_Info__c</attrName><attrType>string</attrType><attrValue>00540000003D8Y4AAK</attrValue></attribute><attribute><attrName>Phone</attrName><attrType>phone</attrType><attrValue>(201) 536-4432</attrValue></attribute><attribute><attrName>Portal_Link__c</attrName><attrType>string</attrType><attrValue>https://na2.salesforce.com/secur/login_portal.jsp?orgId=00D300000000KMl&amp;portalId=060400000004hLP&amp;startURL=/00Q40000014yGLI</attrValue></attribute><attribute><attrName>PostalCode</attrName><attrType>string</attrType><attrValue>10011</attrValue></attribute><attribute><attrName>Primary_SIC__c</attrName><attrType>string</attrType><attrValue>8741</attrValue></attribute><attribute><attrName>RecordTypeId</attrName><attrType>string</attrType><attrValue>0124000000016AoAAI</attrValue></attribute><attribute><attrName>RecordTypeId_account</attrName><attrType>string</attrType><attrValue>0124000000016AkAAI</attrValue></attribute><attribute><attrName>RegionLink__c</attrName><attrType>string</attrType><attrValue>a1R40000002SR8oEAG</attrValue></attribute><attribute><attrName>Region_formula__c</attrName><attrType>string</attrType><attrValue>NAM</attrValue></attribute><attribute><attrName>Region_Lookup__c</attrName><attrType>string</attrType><attrValue>NAM</attrValue></attribute><attribute><attrName>Region_Lookup__c_lead</attrName><attrType>string</attrType><attrValue>NAM</attrValue></attribute><attribute><attrName>Region_Name__c</attrName><attrType>string</attrType><attrValue>AMS_NAM</attrValue></attribute><attribute><attrName>Region_Name__c_lead</attrName><attrType>string</attrType><attrValue>_</attrValue></attribute><attribute><attrName>Region__c_account</attrName><attrType>string</attrType><attrValue>NAM</attrValue></attribute><attribute><attrName>registeredforEAML8</attrName><attrType>boolean</attrType><attrValue>1</attrValue></attribute><attribute><attrName>Registration_Date__c</attrName><attrType>date</attrType><attrValue>2015-02-19</attrValue></attribute><attribute><attrName>Registration_Status__c</attrName><attrType>string</attrType><attrValue>Draft</attrValue></attribute><attribute><attrName>Registration__c</attrName><attrType>string</attrType><attrValue>Reg-251390</attrValue></attribute><attribute><attrName>registry_area_code__c</attrName><attrType>string</attrType><attrValue>612</attrValue></attribute><attribute><attrName>registry_city__c</attrName><attrType>string</attrType><attrValue>Hyderabad</attrValue></attribute><attribute><attrName>registry_company_name__c</attrName><attrType>string</attrType><attrValue>Bharti Airtel</attrValue></attribute><attribute><attrName>registry_country_code3__c</attrName><attrType>string</attrType><attrValue>IND</attrValue></attribute><attribute><attrName>registry_country_code__c</attrName><attrType>string</attrType><attrValue>IN</attrValue></attribute><attribute><attrName>registry_country__c</attrName><attrType>string</attrType><attrValue>India</attrValue></attribute><attribute><attrName>registry_dma_code__c</attrName><attrType>string</attrType><attrValue>613</attrValue></attribute><attribute><attrName>registry_latitude__c</attrName><attrType>float</attrType><attrValue>17.3752994537</attrValue></attribute><attribute><attrName>registry_longitude__c</attrName><attrType>float</attrType><attrValue>78.4744033813</attrValue></attribute><attribute><attrName>registry_state__c</attrName><attrType>string</attrType><attrValue>02</attrValue></attribute><attribute><attrName>Revenue_Range__c</attrName><attrType>string</attrType><attrValue>Over $5B</attrValue></attribute><attribute><attrName>SIC_Code__c</attrName><attrType>string</attrType><attrValue>Software &amp; Technology</attrValue></attribute><attribute><attrName>Specific_Lead_Source__c</attrName><attrType>string</attrType><attrValue>FY16Q1 - MLE - MLW - San Francisco</attrValue></attribute><attribute><attrName>State</attrName><attrType>string</attrType><attrValue>NY</attrValue></attribute><attribute><attrName>Status__c</attrName><attrType>string</attrType><attrValue>Partner Prospect</attrValue></attribute><attribute><attrName>Sub_Industry__c</attrName><attrType>string</attrType><attrValue>Software Applications</attrValue></attribute><attribute><attrName>Sub_Region__c</attrName><attrType>string</attrType><attrValue>NYM</attrValue></attribute><attribute><attrName>Test123__c</attrName><attrType>text</attrType><attrValue>false</attrValue></attribute><attribute><attrName>testBC__c</attrName><attrType>string</attrType><attrValue>United States of America</attrValue></attribute><attribute><attrName>TickerSymbol__c</attrName><attrType>string</attrType><attrValue>BR</attrValue></attribute><attribute><attrName>Title</attrName><attrType>string</attrType><attrValue>NoSQL Architect</attrValue></attribute><attribute><attrName>traffic__c</attrName><attrType>string</attrType><attrValue>Medium</attrValue></attribute><attribute><attrName>Twitter__c</attrName><attrType>url</attrType><attrValue>garyprusso</attrValue></attribute><attribute><attrName>Type__c</attrName><attrType>string</attrType><attrValue>Prospect</attrValue></attribute><attribute><attrName>Ultimate_Parent_OBSOLETE__c</attrName><attrType>string</attrType><attrValue>&lt;a href=\"/0014000001bmrWe\" target=\"_parent\"&gt;Pocket XP, Inc.&lt;/a&gt;</attrValue></attribute><attribute><attrName>User_Segment__c_account</attrName><attrType>string</attrType><attrValue>Channel_AMS</attrValue></attribute><attribute><attrName>user_segment__c_contact</attrName><attrType>string</attrType><attrValue>Alliances</attrValue></attribute><attribute><attrName>Website</attrName><attrType>url</attrType><attrValue>broadridge.com</attrValue></attribute></leadAttributeList></leadRecord>", "geometry":{"type":"Point", "coordinates":[-74.0094471, 40.7464969]}}