{"type":"Feature", "fullDetails":{"firstname":"Jerry", "lastname":"Rickers", "email":"jerry.rickers@marklogic.com", "city":"Mclean", "state":"VA", "industry":"Technology - Software", "company":"MarkLogic Corporation", "id":2866738, "phone":"(703) 919-1770", "accountType":null, "address":"Jones Branch Drive", "country":"United States of America", "numEmployees":null, "username":"jrickers", "region":"AMS_NAM_Northeast_United States of America_VA", "hasAccessToEAML9":true, "postalCode":"22107", "registeredForEAML8":true, "registeredForNoSQLforDummies":false, "registrationDate":"2015-08-31T14:40:18Z", "revenueRange":"$25M - $50M", "leadSource":"MarkLogic Download", "website":"marklogic.com", "marketoLastUpdated":"2016-08-13T02:57:46Z", "appLastUpdated":"2016-08-18T01:04:17.607339-07:00", "dateAdded":"2016-08-18T01:04:17.607339-07:00", "ea_version":["EA2"]}, "geometry":{"type":"Point", "coordinates":[-77.18, 38.93]}}