{"type":"Feature", "properties":{"_id":"5788007c576e24d792a46bb2", "age":40, "eyeColor":"brown", "name":"Bullock Burris", "gender":"male", "company":"MANTRIX", "email":"bullockburris@mantrix.com", "phone":"+1 (912) 440-3182", "address":"437 Erasmus Street, Comptche, Connecticut, 4980", "about":"Incididunt mollit in cillum ut commodo consequat elit consectetur proident sit. Proident non commodo occaecat Lorem do aliquip non pariatur qui nostrud. Duis sit sunt et aliqua culpa incididunt pariatur elit deserunt fugiat. Ullamco ullamco adipisicing mollit aute in cupidatat nulla deserunt. Laboris ad elit sint elit laboris dolore dolore sint quis sunt magna commodo magna. Excepteur sunt est excepteur Lorem do officia.\r\n", "features":["Exospace", "Unia"], "postalCode":97755, "registered":"2015-12-05T01:01:39 +08:00"}, "geometry":{"type":"Point", "coordinates":[57.9579, -2.3934]}}